LICENSE
README.md
setup.py
toy_gradlogp/__init__.py
toy_gradlogp/data.py
toy_gradlogp/energy.py
toy_gradlogp/utils.py
toy_gradlogp/vis.py
toy_gradlogp.egg-info/PKG-INFO
toy_gradlogp.egg-info/SOURCES.txt
toy_gradlogp.egg-info/dependency_links.txt
toy_gradlogp.egg-info/requires.txt
toy_gradlogp.egg-info/top_level.txt
toy_gradlogp/run/__init__.py
toy_gradlogp/run/train_energy.py