Metadata-Version: 2.1
Name: toy-gradlogp
Version: 0.2.1
Summary: Some toy examples of score matching algorithms written in PyTorch
Home-page: https://github.com/Ending2015a/toy_gradlogp
Author: JoeHsiao
Author-email: joehsiao@gapp.nthu.edu.tw
License: MIT
Keywords: score-matching playform pytorch
Platform: UNKNOWN
Classifier: Development Status :: 2 - Pre-Alpha
Classifier: Intended Audience :: Science/Research
Classifier: Topic :: Scientific/Engineering :: Artificial Intelligence
Classifier: Topic :: Software Development :: Libraries :: Python Modules
Classifier: License :: OSI Approved :: MIT License
Classifier: Programming Language :: Python :: 3.6
Classifier: Programming Language :: Python :: 3.7
Classifier: Programming Language :: Python :: 3.8
Classifier: Programming Language :: Python :: 3.9
Requires-Python: >=3.6
License-File: LICENSE
